just/__init__.py
just/base_task_param.py
just/baseclient.py
just/justclient.py
just/justerror.py
just/offline_task_param.py
just/realtime_task_param.py
just/resultset.py
just/stable.py
just/taskclient.py
just_db_driver-1.0.9.dist-info/METADATA
just_db_driver-1.0.9.dist-info/WHEEL
just_db_driver-1.0.9.dist-info/top_level.txt
just_db_driver-1.0.9.dist-info/RECORD
